SimPel/Calculations.py
SimPel/Initialize.py
SimPel/Readfile.py
SimPel/SimPel.py
SimPel/SimPelIcon.png
SimPel/SimPel_Layout.py
SimPel/SimPel_config_GUI.py
SimPel/SimPel_icon.ico
SimPel/SimPel_icon.png
SimPel/SimPel_splashicon.png
SimPel/__init__.py
SimPel-1.0.3a0.dist-info/LICENSE.txt
SimPel-1.0.3a0.dist-info/METADATA
SimPel-1.0.3a0.dist-info/WHEEL
SimPel-1.0.3a0.dist-info/entry_points.txt
SimPel-1.0.3a0.dist-info/top_level.txt
SimPel-1.0.3a0.dist-info/RECORD
