Metadata-Version: 2.1
Name: SimPel
Version: 1.0.3a0
Summary: Simulation of PELDOR time traces
Home-page: https://www.radicals.uni-freiburg.de/de/software/simpel
Author: Stephan Rein
Author-email: stephan.rein@physchem.uni-freiburg.de
License: GPLv3
Keywords: EPR simulations,DEER,PELDOR,Dipolar spectroscopy
Platform: UNKNOWN
Classifier: Programming Language :: Python :: 3.5
Classifier: Programming Language :: Python :: 3.6
Classifier: Programming Language :: Python :: 3.7
Classifier: Programming Language :: Python :: 3.8
Classifier: License :: OSI Approved :: GNU General Public License v3 (GPLv3)
Classifier: Operating System :: OS Independent
Classifier: Intended Audience :: Science/Research
Classifier: Topic :: Scientific/Engineering :: Physics
Requires-Python: >=3.5
Requires-Dist: numpy (>=1.15.4)
Requires-Dist: PyQt5 (>=5.11.3)
Requires-Dist: PyQt5-sip (>=4.19.13)
Requires-Dist: numpydoc (>=0.9.1)
Requires-Dist: scipy (==1.2.0)
Requires-Dist: matplotlib (>=3.0.2)
